kvikio/GIT_COMMIT
kvikio/VERSION
kvikio/__init__.py
kvikio/_version.py
kvikio/buffer.py
kvikio/cufile.py
kvikio/cufile_driver.py
kvikio/defaults.py
kvikio/mmap.py
kvikio/numcodecs.py
kvikio/numpy.py
kvikio/remote_file.py
kvikio/utils.py
kvikio/_lib/__init__.pxd
kvikio/_lib/__init__.py
kvikio/_lib/arr.cpython-312-x86_64-linux-gnu.so
kvikio/_lib/arr.pxd
kvikio/_lib/arr.pyi
kvikio/_lib/buffer.cpython-312-x86_64-linux-gnu.so
kvikio/_lib/cufile_driver.cpython-312-x86_64-linux-gnu.so
kvikio/_lib/defaults.cpython-312-x86_64-linux-gnu.so
kvikio/_lib/file_handle.cpython-312-x86_64-linux-gnu.so
kvikio/_lib/future.cpython-312-x86_64-linux-gnu.so
kvikio/_lib/future.pxd
kvikio/_lib/mmap.cpython-312-x86_64-linux-gnu.so
kvikio/_lib/remote_handle.cpython-312-x86_64-linux-gnu.so
kvikio/benchmarks/__init__.py
kvikio/benchmarks/http_io.py
kvikio/benchmarks/s3_io.py
kvikio/benchmarks/single_node_io.py
kvikio/benchmarks/utils.py
kvikio/benchmarks/zarr_io.py
kvikio/zarr/__init__.py
kvikio/zarr/_zarr_python_3.py
kvikio_cu13-25.12.0.dist-info/METADATA
kvikio_cu13-25.12.0.dist-info/WHEEL
kvikio_cu13-25.12.0.dist-info/RECORD
kvikio_cu13-25.12.0.dist-info/licenses/LICENSE
