Metadata-Version: 2.1
Name: kvikio-cu13
Version: 25.12.0
Summary: KvikIO - GPUDirect Storage
Author: NVIDIA Corporation
License: Apache-2.0
Classifier: Intended Audience :: Developers
Classifier: Topic :: Database
Classifier: Topic :: Scientific/Engineering
Classifier: License :: OSI Approved :: Apache Software License
Classifier: Programming Language :: Python
Classifier: Programming Language :: Python :: 3.10
Classifier: Programming Language :: Python :: 3.11
Classifier: Programming Language :: Python :: 3.12
Classifier: Programming Language :: Python :: 3.13
Project-URL: Homepage, https://github.com/rapidsai/kvikio
Requires-Python: >=3.10
Requires-Dist: cupy-cuda13x>=13.6.0
Requires-Dist: libkvikio-cu13==25.12.*
Requires-Dist: numpy<3.0a0,>=1.23
Requires-Dist: packaging
Provides-Extra: test
Requires-Dist: boto3>=1.21.21; extra == "test"
Requires-Dist: cuda-python<14.0a0,>=13.0.1; extra == "test"
Requires-Dist: moto[server]>=4.0.8; extra == "test"
Requires-Dist: pytest-asyncio; extra == "test"
Requires-Dist: pytest-cov; extra == "test"
Requires-Dist: pytest-timeout; extra == "test"
Requires-Dist: pytest<9.0.0a0; extra == "test"
Requires-Dist: rangehttpserver; extra == "test"
Requires-Dist: rapids-dask-dependency==25.12.*; extra == "test"
Requires-Dist: zarr<3.2.0a0,<4.0.0,>=3.0.0; python_version >= "3.11" and extra == "test"
Provides-Extra: zarr
Requires-Dist: zarr<3.2.0a0,<4.0.0,>=3.0.0; python_version >= "3.11" and extra == "zarr"
